<?xml version='1.0' encoding='utf-8'?>
<annotation>
  <folder>images</folder>
  <filename>(2018).jpg</filename>
  <path>D:\呈仲\ultralytics\unlabeled_images\image\(2018).jpg</path>
  <source>
    <database>Unknown</database>
  </source>
  <size>
    <width>2960</width>
    <height>1668</height>
    <depth>3</depth>
  </size>
  <segmented>0</segmented>
  <object>
    <name>People</name>
    <pose>Unspecified</pose>
    <truncated>0</truncated>
    <difficult>0</difficult>
    <confidence>0.916687</confidence>
    <bndbox>
      <xmin>1875</xmin>
      <ymin>899</ymin>
      <xmax>2410</xmax>
      <ymax>1664</ymax>
    </bndbox>
  </object>
  <object>
    <name>People</name>
    <pose>Unspecified</pose>
    <truncated>0</truncated>
    <difficult>0</difficult>
    <confidence>0.891532</confidence>
    <bndbox>
      <xmin>2330</xmin>
      <ymin>780</ymin>
      <xmax>2642</xmax>
      <ymax>1440</ymax>
    </bndbox>
  </object>
  <object>
    <name>Clothes</name>
    <pose>Unspecified</pose>
    <truncated>0</truncated>
    <difficult>0</difficult>
    <confidence>0.860933</confidence>
    <bndbox>
      <xmin>2373</xmin>
      <ymin>942</ymin>
      <xmax>2627</xmax>
      <ymax>1299</ymax>
    </bndbox>
  </object>
  <object>
    <name>Clothes</name>
    <pose>Unspecified</pose>
    <truncated>0</truncated>
    <difficult>0</difficult>
    <confidence>0.834142</confidence>
    <bndbox>
      <xmin>1932</xmin>
      <ymin>1151</ymin>
      <xmax>2390</xmax>
      <ymax>1609</ymax>
    </bndbox>
  </object>
  <object>
    <name>Face Mask</name>
    <pose>Unspecified</pose>
    <truncated>0</truncated>
    <difficult>0</difficult>
    <confidence>0.808537</confidence>
    <bndbox>
      <xmin>2089</xmin>
      <ymin>901</ymin>
      <xmax>2248</xmax>
      <ymax>1027</ymax>
    </bndbox>
  </object>
  <object>
    <name>Hat</name>
    <pose>Unspecified</pose>
    <truncated>0</truncated>
    <difficult>0</difficult>
    <confidence>0.799826</confidence>
    <bndbox>
      <xmin>2167</xmin>
      <ymin>945</ymin>
      <xmax>2303</xmax>
      <ymax>1093</ymax>
    </bndbox>
  </object>
  <object>
    <name>Glove</name>
    <pose>Unspecified</pose>
    <truncated>0</truncated>
    <difficult>0</difficult>
    <confidence>0.793178</confidence>
    <bndbox>
      <xmin>2546</xmin>
      <ymin>1165</ymin>
      <xmax>2625</xmax>
      <ymax>1320</ymax>
    </bndbox>
  </object>
  <object>
    <name>Dust Mask</name>
    <pose>Unspecified</pose>
    <truncated>0</truncated>
    <difficult>0</difficult>
    <confidence>0.789283</confidence>
    <bndbox>
      <xmin>2461</xmin>
      <ymin>896</ymin>
      <xmax>2521</xmax>
      <ymax>963</ymax>
    </bndbox>
  </object>
  <object>
    <name>Glove</name>
    <pose>Unspecified</pose>
    <truncated>0</truncated>
    <difficult>0</difficult>
    <confidence>0.766733</confidence>
    <bndbox>
      <xmin>2336</xmin>
      <ymin>1109</ymin>
      <xmax>2421</xmax>
      <ymax>1268</ymax>
    </bndbox>
  </object>
  <object>
    <name>Face Mask</name>
    <pose>Unspecified</pose>
    <truncated>0</truncated>
    <difficult>0</difficult>
    <confidence>0.743293</confidence>
    <bndbox>
      <xmin>2452</xmin>
      <ymin>786</ymin>
      <xmax>2553</xmax>
      <ymax>876</ymax>
    </bndbox>
  </object>
  <object>
    <name>Hat</name>
    <pose>Unspecified</pose>
    <truncated>0</truncated>
    <difficult>0</difficult>
    <confidence>0.634244</confidence>
    <bndbox>
      <xmin>2457</xmin>
      <ymin>815</ymin>
      <xmax>2540</xmax>
      <ymax>892</ymax>
    </bndbox>
  </object>
  <object>
    <name>Glove</name>
    <pose>Unspecified</pose>
    <truncated>0</truncated>
    <difficult>0</difficult>
    <confidence>0.574149</confidence>
    <bndbox>
      <xmin>1887</xmin>
      <ymin>1358</ymin>
      <xmax>1963</xmax>
      <ymax>1484</ymax>
    </bndbox>
  </object>
</annotation>