<?xml version='1.0' encoding='utf-8'?>
<annotation>
  <folder>images</folder>
  <filename>(2344).jpg</filename>
  <path>D:\呈仲\ultralytics\unlabeled_images\image\(2344).jpg</path>
  <source>
    <database>Unknown</database>
  </source>
  <size>
    <width>2960</width>
    <height>1668</height>
    <depth>3</depth>
  </size>
  <segmented>0</segmented>
  <object>
    <name>People</name>
    <pose>Unspecified</pose>
    <truncated>0</truncated>
    <difficult>0</difficult>
    <confidence>0.927064</confidence>
    <bndbox>
      <xmin>2079</xmin>
      <ymin>809</ymin>
      <xmax>2543</xmax>
      <ymax>1667</ymax>
    </bndbox>
  </object>
  <object>
    <name>Clothes</name>
    <pose>Unspecified</pose>
    <truncated>0</truncated>
    <difficult>0</difficult>
    <confidence>0.894306</confidence>
    <bndbox>
      <xmin>2178</xmin>
      <ymin>954</ymin>
      <xmax>2529</xmax>
      <ymax>1361</ymax>
    </bndbox>
  </object>
  <object>
    <name>Glove</name>
    <pose>Unspecified</pose>
    <truncated>0</truncated>
    <difficult>0</difficult>
    <confidence>0.773488</confidence>
    <bndbox>
      <xmin>2102</xmin>
      <ymin>1165</ymin>
      <xmax>2192</xmax>
      <ymax>1305</ymax>
    </bndbox>
  </object>
  <object>
    <name>Hat</name>
    <pose>Unspecified</pose>
    <truncated>0</truncated>
    <difficult>0</difficult>
    <confidence>0.475888</confidence>
    <bndbox>
      <xmin>2324</xmin>
      <ymin>808</ymin>
      <xmax>2397</xmax>
      <ymax>894</ymax>
    </bndbox>
  </object>
  <object>
    <name>Shoes</name>
    <pose>Unspecified</pose>
    <truncated>0</truncated>
    <difficult>0</difficult>
    <confidence>0.444473</confidence>
    <bndbox>
      <xmin>2257</xmin>
      <ymin>1577</ymin>
      <xmax>2339</xmax>
      <ymax>1663</ymax>
    </bndbox>
  </object>
  <object>
    <name>Hat</name>
    <pose>Unspecified</pose>
    <truncated>0</truncated>
    <difficult>0</difficult>
    <confidence>0.327141</confidence>
    <bndbox>
      <xmin>2368</xmin>
      <ymin>830</ymin>
      <xmax>2419</xmax>
      <ymax>912</ymax>
    </bndbox>
  </object>
</annotation>